rootlp/__init__.py
rootlp/modules/Section_LP/Section.py
rootlp/modules/Section_LP/__init__.py
rootlp/modules/Section_LP/_functions/__init__.py
rootlp/modules/Section_LP/_functions/__template__.py
rootlp/modules/Section_LP/test_Section.py
rootlp/modules/__init__.py
rootlp/modules/execution_panel_LP/__init__.py
rootlp/modules/execution_panel_LP/_functions/__init__.py
rootlp/modules/execution_panel_LP/_functions/__template__.py
rootlp/modules/execution_panel_LP/execution_panel.py
rootlp/modules/execution_panel_LP/test_execution_panel.py
rootlp/modules/main_LP/__init__.py
rootlp/modules/main_LP/_functions/__init__.py
rootlp/modules/main_LP/_functions/__template__.py
rootlp/modules/main_LP/main.py
rootlp/modules/main_LP/test_main.py
rootlp/modules/menu_LP/__init__.py
rootlp/modules/menu_LP/_functions/__init__.py
rootlp/modules/menu_LP/_functions/__template__.py
rootlp/modules/menu_LP/menu.py
rootlp/modules/menu_LP/test_menu.py
rootlp/modules/mo_LP/__init__.py
rootlp/modules/mo_LP/_functions/__init__.py
rootlp/modules/mo_LP/_functions/__template__.py
rootlp/modules/mo_LP/mo.py
rootlp/modules/mo_LP/test_mo.py
rootlp/modules/overview_LP/__init__.py
rootlp/modules/overview_LP/_functions/__init__.py
rootlp/modules/overview_LP/_functions/__template__.py
rootlp/modules/overview_LP/overview.py
rootlp/modules/overview_LP/test_overview.py
rootlp/modules/print_LP/__init__.py
rootlp/modules/print_LP/_functions/__init__.py
rootlp/modules/print_LP/_functions/__template__.py
rootlp/modules/print_LP/print.py
rootlp/modules/print_LP/test_print.py
rootlp/modules/project_server_LP/__init__.py
rootlp/modules/project_server_LP/_functions/__init__.py
rootlp/modules/project_server_LP/_functions/__template__.py
rootlp/modules/project_server_LP/project_server.py
rootlp/modules/project_server_LP/test_project_server.py
rootlp/modules/raw_code_LP/__init__.py
rootlp/modules/raw_code_LP/_functions/__init__.py
rootlp/modules/raw_code_LP/_functions/__template__.py
rootlp-0.1.14.dist-info/WHEEL
rootlp-0.1.14.dist-info/METADATA
rootlp-0.1.14.dist-info/RECORD
