Metadata-Version: 2.3
Name: rootlp
Version: 0.1.14
Summary: A library that gathers root functions for custom script execution.
Requires-Dist: corelp
Requires-Dist: joblib
Requires-Dist: marimo
Requires-Dist: psutil
Requires-Dist: rich
Requires-Python: >=3.12
